si_convert/si_convert.py
si_convert/si_data.py
si_convert-1.1.0.dist-info/LICENSE.md
si_convert-1.1.0.dist-info/METADATA
si_convert-1.1.0.dist-info/WHEEL
si_convert-1.1.0.dist-info/entry_points.txt
si_convert-1.1.0.dist-info/top_level.txt
si_convert-1.1.0.dist-info/RECORD
