Metadata-Version: 2.1
Name: si_convert
Version: 1.1.0
Summary: CLI tool for converting between SIQ and YAML for "Svoya Igra" (similar to Jeopardy)
Home-page: https://github.com/Zverik/si_convert
Author: Ilya Zverev
Author-email: ilya@zverev.info
Classifier: Development Status :: 4 - Beta
Classifier: Environment :: Console
Classifier: Intended Audience :: Information Technology
Classifier: Intended Audience :: Customer Service
Classifier: Operating System :: OS Independent
Classifier: License :: OSI Approved :: ISC License (ISCL)
Classifier: Programming Language :: Python :: 3
Requires-Python: !=3.0.*,!=3.1.*,!=3.2.*,>=2.7
License-File: LICENSE.md
Requires-Dist: pyyaml
